{
  "aggregate": {
    "bad_prediction_count_mean": 0,
    "bad_prediction_count_sd": 0,
    "capped_pp_calibration_gap_mean": -0.0158,
    "capped_pp_calibration_gap_sd": 0.0726,
    "capped_pp_gini_mean": 0.1832,
    "capped_pp_gini_sd": 0.0241,
    "capped_pp_mae_mean": 217.4309,
    "capped_pp_mae_sd": 2.6716,
    "capped_pp_observed_loss_cost_mean": 115.3648,
    "capped_pp_observed_loss_cost_sd": 5.0877,
    "capped_pp_predicted_loss_cost_mean": 113.3051,
    "capped_pp_predicted_loss_cost_sd": 3.7898,
    "capped_pp_rmse_mean": 2533.3689,
    "capped_pp_rmse_sd": 504.4904,
    "capped_severity_aic_mean": null,
    "capped_severity_aic_sd": null,
    "capped_severity_bic_mean": null,
    "capped_severity_bic_sd": null,
    "capped_severity_gamma_deviance_mean": 1.1746,
    "capped_severity_gamma_deviance_sd": 0.0768,
    "capped_severity_mae_mean": 1229.644,
    "capped_severity_mae_sd": 35.3715,
    "capped_severity_rmse_mean": 3340.5407,
    "capped_severity_rmse_sd": 305.8957,
    "claim_rows_mean": 4313.6667,
    "claim_rows_sd": 11.5902,
    "fold_mean": 2,
    "fold_sd": 1,
    "frequency_aic_mean": null,
    "frequency_aic_sd": null,
    "frequency_bic_mean": null,
    "frequency_bic_sd": null,
    "frequency_gini_mean": 0.1798,
    "frequency_gini_sd": 0.0069,
    "frequency_mae_mean": 0.1324,
    "frequency_mae_sd": 0.0001,
    "frequency_poisson_deviance_mean": 0.2511,
    "frequency_poisson_deviance_sd": 0.0006,
    "frequency_rmse_mean": 0.4745,
    "frequency_rmse_sd": 0.0124,
    "max_abs_coefficient_mean": null,
    "max_abs_coefficient_sd": null,
    "observed_claims_mean": 4313.6667,
    "observed_claims_sd": 11.5902,
    "parameter_count_mean": null,
    "parameter_count_sd": null,
    "policies_mean": 110178.3333,
    "policies_sd": 0.5774,
    "policy_leakage_count_mean": 0,
    "policy_leakage_count_sd": 0,
    "predicted_claims_mean": 4307.4267,
    "predicted_claims_sd": 3.2683,
    "raw_pp_calibration_gap_mean": -0.0522,
    "raw_pp_calibration_gap_sd": 0.2214,
    "raw_pp_gini_mean": 0.1983,
    "raw_pp_gini_sd": 0.1322,
    "raw_pp_mae_mean": 264.657,
    "raw_pp_mae_sd": 16.6179,
    "raw_pp_observed_loss_cost_mean": 143.8666,
    "raw_pp_observed_loss_cost_sd": 18.3964,
    "raw_pp_predicted_loss_cost_mean": 134.0043,
    "raw_pp_predicted_loss_cost_sd": 16.5133,
    "raw_pp_rmse_mean": 7279.9138,
    "raw_pp_rmse_sd": 3422.7752,
    "raw_severity_gamma_deviance_mean": 1.6456,
    "raw_severity_gamma_deviance_sd": 0.2366,
    "raw_severity_mae_mean": 1849.7511,
    "raw_severity_mae_sd": 223.6615,
    "raw_severity_rmse_mean": 13017.8085,
    "raw_severity_rmse_sd": 9163.9207,
    "severity_aic_mean": null,
    "severity_aic_sd": null,
    "severity_bic_mean": null,
    "severity_bic_sd": null
  },
  "candidate": {
    "actuarial_rationale": "High regularization.",
    "description": "12/20 leaves + very high min_data (2000+). Simpler model.",
    "hypothesis": "Simpler model may generalize better.",
    "id": "lightgbm_12_20_high_min",
    "is_baseline": false,
    "lightgbm": {
      "capped_severity_grid": [
        {
          "bagging_fraction": 0.86,
          "feature_fraction": 0.86,
          "lambda_l2": 9,
          "learning_rate": 0.04,
          "min_data_in_leaf": 260,
          "num_leaves": 6
        },
        {
          "bagging_fraction": 0.86,
          "feature_fraction": 0.81,
          "lambda_l2": 7,
          "learning_rate": 0.035,
          "min_data_in_leaf": 200,
          "num_leaves": 10
        }
      ],
      "early_stopping_rounds": 16,
      "frequency_grid": [
        {
          "bagging_fraction": 0.86,
          "feature_fraction": 0.86,
          "lambda_l2": 11,
          "learning_rate": 0.04,
          "min_data_in_leaf": 2100,
          "num_leaves": 12
        },
        {
          "bagging_fraction": 0.86,
          "feature_fraction": 0.81,
          "lambda_l2": 9,
          "learning_rate": 0.035,
          "min_data_in_leaf": 1700,
          "num_leaves": 20
        }
      ],
      "nrounds": 130,
      "severity_grid": [
        {
          "bagging_fraction": 0.86,
          "feature_fraction": 0.86,
          "lambda_l2": 9,
          "learning_rate": 0.04,
          "min_data_in_leaf": 260,
          "num_leaves": 6
        },
        {
          "bagging_fraction": 0.86,
          "feature_fraction": 0.81,
          "lambda_l2": 7,
          "learning_rate": 0.035,
          "min_data_in_leaf": 200,
          "num_leaves": 10
        }
      ]
    },
    "model_type": "lightgbm"
  },
  "candidate_id": "lightgbm_12_20_high_min",
  "decision": {
    "deltas": {
      "pricing_capped_calibration_abs": 0.0158,
      "pricing_capped_gini_gain": 0.00040000000000001146,
      "pricing_capped_mae_deterioration": -0.0004045625460591878,
      "pricing_capped_rmse_deterioration": -1.4605036780646054e-06,
      "pricing_champion_capped_calibration_abs": 0.0147,
      "pricing_raw_gini_gain": -0.0007999999999999952,
      "segmentation_capped_calibration_deterioration": 0.0013000000000000008,
      "segmentation_capped_gini_gain": 0.0005000000000000004,
      "segmentation_capped_mae_deterioration": -0.0008896057199442321,
      "segmentation_capped_rmse_deterioration": -4.263079869163498e-06,
      "segmentation_fold_agreement": 2,
      "segmentation_raw_gini_gain": 0.0002999999999999947
    },
    "gate_failures": [
      "pricing_material_improvement",
      "segmentation_minimum_capped_gini_gain"
    ],
    "gate_results": {
      "finite_nonnegative_predictions": true,
      "loss_reconciliation": true,
      "no_policy_leakage": true,
      "pricing_capped_calibration_tight": true,
      "pricing_capped_gini_not_materially_worse": true,
      "pricing_capped_mae_tolerance": true,
      "pricing_capped_rmse_tolerance": true,
      "pricing_material_improvement": false,
      "pricing_raw_gini_not_materially_worse": true,
      "pricing_transparent_model_or_documented_blend": true,
      "segmentation_capped_calibration_tolerance": true,
      "segmentation_capped_mae_tolerance": true,
      "segmentation_capped_rmse_tolerance": true,
      "segmentation_minimum_capped_gini_gain": false,
      "segmentation_minimum_fold_agreement": true,
      "segmentation_raw_gini_not_materially_worse": true
    },
    "pricing_status": "not_pricing",
    "segmentation_status": "not_segmentation",
    "selection_score": 0.17925,
    "status": "discard"
  },
  "diagnostics": {
    "raw_counts": {
      "freq_rows": 413169,
      "sev_rows": 16181
    }
  },
  "fold_metrics": [
    {
      "bad_prediction_count": 0,
      "capped_pp_calibration_gap": 0.0119,
      "capped_pp_gini": 0.2056,
      "capped_pp_mae": 219.0473,
      "capped_pp_observed_loss_cost": 114.5376,
      "capped_pp_predicted_loss_cost": 115.9026,
      "capped_pp_rmse": 2872.8764,
      "capped_severity_aic": null,
      "capped_severity_bic": null,
      "capped_severity_gamma_deviance": 1.1432,
      "capped_severity_mae": 1241.5961,
      "capped_severity_rmse": 3313.9899,
      "claim_rows": 4303,
      "fold": 1,
      "frequency_aic": null,
      "frequency_bic": null,
      "frequency_gini": 0.1749,
      "frequency_mae": 0.1322,
      "frequency_poisson_deviance": 0.2513,
      "frequency_rmse": 0.4883,
      "max_abs_coefficient": null,
      "observed_claims": 4303,
      "parameter_count": null,
      "policies": 110179,
      "policy_leakage_count": 0,
      "predicted_claims": 4305.4786,
      "raw_pp_calibration_gap": -0.1693,
      "raw_pp_gini": 0.3364,
      "raw_pp_mae": 282.9259,
      "raw_pp_observed_loss_cost": 161.7107,
      "raw_pp_predicted_loss_cost": 134.338,
      "raw_pp_rmse": 10001.2263,
      "raw_severity_gamma_deviance": 1.8404,
      "raw_severity_mae": 2105.1247,
      "raw_severity_rmse": 23501.6732,
      "severity_aic": null,
      "severity_bic": null
    },
    {
      "bad_prediction_count": 0,
      "capped_pp_calibration_gap": -0.0982,
      "capped_pp_gini": 0.1577,
      "capped_pp_mae": 218.8982,
      "capped_pp_observed_loss_cost": 120.8154,
      "capped_pp_predicted_loss_cost": 108.9564,
      "capped_pp_rmse": 2773.5682,
      "capped_severity_aic": null,
      "capped_severity_bic": null,
      "capped_severity_gamma_deviance": 1.2621,
      "capped_severity_mae": 1257.4911,
      "capped_severity_rmse": 3658.8463,
      "claim_rows": 4312,
      "fold": 2,
      "frequency_aic": null,
      "frequency_bic": null,
      "frequency_gini": 0.1768,
      "frequency_mae": 0.1324,
      "frequency_poisson_deviance": 0.2504,
      "frequency_rmse": 0.4707,
      "max_abs_coefficient": null,
      "observed_claims": 4312,
      "parameter_count": null,
      "policies": 110178,
      "policy_leakage_count": 0,
      "predicted_claims": 4311.1999,
      "raw_pp_calibration_gap": -0.1904,
      "raw_pp_gini": 0.0728,
      "raw_pp_mae": 250.4392,
      "raw_pp_observed_loss_cost": 144.9254,
      "raw_pp_predicted_loss_cost": 117.3266,
      "raw_pp_rmse": 8401.441,
      "raw_severity_gamma_deviance": 1.7142,
      "raw_severity_mae": 1688.7073,
      "raw_severity_rmse": 9018.4047,
      "severity_aic": null,
      "severity_bic": null
    },
    {
      "bad_prediction_count": 0,
      "capped_pp_calibration_gap": 0.039,
      "capped_pp_gini": 0.1863,
      "capped_pp_mae": 214.3472,
      "capped_pp_observed_loss_cost": 110.7413,
      "capped_pp_predicted_loss_cost": 115.0564,
      "capped_pp_rmse": 1953.662,
      "capped_severity_aic": null,
      "capped_severity_bic": null,
      "capped_severity_gamma_deviance": 1.1185,
      "capped_severity_mae": 1189.8448,
      "capped_severity_rmse": 3048.7857,
      "claim_rows": 4326,
      "fold": 3,
      "frequency_aic": null,
      "frequency_bic": null,
      "frequency_gini": 0.1876,
      "frequency_mae": 0.1325,
      "frequency_poisson_deviance": 0.2515,
      "frequency_rmse": 0.4644,
      "max_abs_coefficient": null,
      "observed_claims": 4326,
      "parameter_count": null,
      "policies": 110178,
      "policy_leakage_count": 0,
      "predicted_claims": 4305.6015,
      "raw_pp_calibration_gap": 0.2031,
      "raw_pp_gini": 0.1857,
      "raw_pp_mae": 260.606,
      "raw_pp_observed_loss_cost": 124.9636,
      "raw_pp_predicted_loss_cost": 150.3481,
      "raw_pp_rmse": 3437.0743,
      "raw_severity_gamma_deviance": 1.3823,
      "raw_severity_mae": 1755.4213,
      "raw_severity_rmse": 6533.3476,
      "severity_aic": null,
      "severity_bic": null
    }
  ],
  "integrity": {
    "bad_prediction_count": 0,
    "loss_reconciliation_gap": 0,
    "policy_leakage_count": 0
  },
  "log_truncated": false,
  "model_type": "lightgbm",
  "outer_folds": 3,
  "runtime_seconds": 20.03287,
  "seed": 20260423,
  "severity_cap": 36876.2,
  "status": "ok",
  "timed_out": false
}
