{
  "actuarial_rationale": "More leaves = more capacity. Keep regularization high to prevent overfit.",
  "description": "Best now at Gini 0.1851, -0.98% calibration. Try more leaves (16-28) to capture more complex patterns.",
  "hypothesis": "Previous run 0.1851 was better. Try more leaves for more capacity. May capture finer risk segments.",
  "id": "lightgbm_even_more_leaves",
  "is_baseline": false,
  "lightgbm": {
    "capped_severity_grid": [
      {
        "bagging_fraction": 0.87,
        "feature_fraction": 0.87,
        "lambda_l2": 8,
        "learning_rate": 0.04,
        "min_data_in_leaf": 180,
        "num_leaves": 8
      },
      {
        "bagging_fraction": 0.87,
        "feature_fraction": 0.82,
        "lambda_l2": 6,
        "learning_rate": 0.035,
        "min_data_in_leaf": 140,
        "num_leaves": 12
      }
    ],
    "early_stopping_rounds": 15,
    "frequency_grid": [
      {
        "bagging_fraction": 0.87,
        "feature_fraction": 0.87,
        "lambda_l2": 10,
        "learning_rate": 0.04,
        "min_data_in_leaf": 1500,
        "num_leaves": 16
      },
      {
        "bagging_fraction": 0.87,
        "feature_fraction": 0.82,
        "lambda_l2": 8,
        "learning_rate": 0.035,
        "min_data_in_leaf": 1200,
        "num_leaves": 28
      }
    ],
    "nrounds": 120,
    "severity_grid": [
      {
        "bagging_fraction": 0.87,
        "feature_fraction": 0.87,
        "lambda_l2": 8,
        "learning_rate": 0.04,
        "min_data_in_leaf": 180,
        "num_leaves": 8
      },
      {
        "bagging_fraction": 0.87,
        "feature_fraction": 0.82,
        "lambda_l2": 6,
        "learning_rate": 0.035,
        "min_data_in_leaf": 140,
        "num_leaves": 12
      }
    ]
  },
  "model_type": "lightgbm"
}
